currency_codes/__init__.py
currency_codes/assets/__init__.py
currency_codes/assets/crypto.py
currency_codes/assets/fiat.py
currency_codes/assets/other.py
currency_codes/exceptions.py
currency_codes/main.py
currency_codes/models.py
currency_codes-23.6.4.dist-info/LICENSE
currency_codes-23.6.4.dist-info/METADATA
currency_codes-23.6.4.dist-info/WHEEL
currency_codes-23.6.4.dist-info/RECORD
