Metadata-Version: 2.1
Name: currency-codes
Version: 23.6.4
Summary: Comprehensive Python package for managing currency codes across different types of assets
Home-page: https://github.com/duketemon/currency_codes/blob/main/README.md#description
Keywords: ISO 4217,ISO-4217,Currency Codes,Currencies,fiat,crypto,commodity
Author: Artem Kuchumov
Author-email: duketemon@gmail.com
Requires-Python: >=3.7.2,<4.0.0
Classifier: Programming Language :: Python :: 3
Classifier: Programming Language :: Python :: 3.8
Classifier: Programming Language :: Python :: 3.9
Classifier: Programming Language :: Python :: 3.10
Classifier: Programming Language :: Python :: 3.11
Project-URL: Repository, https://github.com/duketemon/currency_codes
